.DS_Store
paubox/__init__.py
paubox/paubox.py
paubox/helpers/__init__.py
paubox/helpers/errors.py
paubox/helpers/mail.py
tests/__init__.py
tests/test_paubox.py
paubox_python3-1.0.1.dist-info/LICENSE
paubox_python3-1.0.1.dist-info/METADATA
paubox_python3-1.0.1.dist-info/WHEEL
paubox_python3-1.0.1.dist-info/top_level.txt
paubox_python3-1.0.1.dist-info/RECORD
