Metadata-Version: 2.1
Name: paubox-python3
Version: 1.0.1
Summary: Python3 SDK for Paubox Email REST API
Home-page: https://github.com/Paubox/paubox-python3
Author: Paubox
Author-email: info@paubox.com
License: UNKNOWN
Platform: UNKNOWN
Classifier: Programming Language :: Python :: 3.8
Classifier: License :: OSI Approved :: Apache Software License
Requires-Dist: requests
